half_orm_packager/__init__.py
half_orm_packager/globals.py
half_orm_packager/hgit.py
half_orm_packager/hop.py
half_orm_packager/patch.py
half_orm_packager/test.py
half_orm_packager/update.py
half_orm_packager/utils.py
half_orm_packager/version.txt
half_orm_packager/db_patch_system/README
half_orm_packager/db_patch_system/half_orm_meta.hop_release.sql
half_orm_packager/db_patch_system/half_orm_meta.hop_release_issue.sql
half_orm_packager/db_patch_system/half_orm_meta.view.hop_last_release.sql
half_orm_packager/db_patch_system/half_orm_meta.view.hop_penultimate_release.sql
half_orm_packager/templates/.gitignore
half_orm_packager/templates/MANIFEST.in
half_orm_packager/templates/Pipfile
half_orm_packager/templates/README
half_orm_packager/templates/base_test
half_orm_packager/templates/config
half_orm_packager/templates/db_connector.py
half_orm_packager/templates/fkeys_properties
half_orm_packager/templates/module_template_1
half_orm_packager/templates/module_template_2
half_orm_packager/templates/module_template_3
half_orm_packager/templates/relation_test
half_orm_packager/templates/setup.py
half_orm_packager/templates/warning
half_orm_packager-0.0.27.dist-info/METADATA
half_orm_packager-0.0.27.dist-info/WHEEL
half_orm_packager-0.0.27.dist-info/entry_points.txt
half_orm_packager-0.0.27.dist-info/top_level.txt
half_orm_packager-0.0.27.dist-info/RECORD
