Metadata-Version: 2.1
Name: half-orm-packager
Version: 0.0.27
Summary: half_orm packager.
Home-page: https://github.com/collorg/halfORM_packager
Author: Joël Maïzi
Author-email: joel.maizi@collorg.org
License: GNU General Public License v3 (GPLv3)
Keywords: postgres,relation-object mapping
Classifier: Development Status :: 3 - Alpha
Classifier: Intended Audience :: Developers
Classifier: Topic :: Software Development :: Build Tools
Classifier: License :: OSI Approved :: GNU General Public License v3 (GPLv3)
Classifier: Programming Language :: Python :: 3.6
Classifier: Programming Language :: Python :: 3.7
Classifier: Programming Language :: Python :: 3.8
Requires-Dist: GitPython
Requires-Dist: click
Requires-Dist: pydash
Requires-Dist: half-orm (>=0.7.4)
